README.md
setup.py
django_lare/__init__.py
django_lare/context_processors.py
django_lare/middlewares.py
django_lare/mixins.py
django_lare/models.py
django_lare/test_settings.py
django_lare/test_views.py
django_lare/tests.py
django_lare/urls.py
django_lare.egg-info/PKG-INFO
django_lare.egg-info/SOURCES.txt
django_lare.egg-info/dependency_links.txt
django_lare.egg-info/top_level.txt
django_lare/__pycache__/__init__.cpython-36.pyc
django_lare/__pycache__/context_processors.cpython-36.pyc
django_lare/__pycache__/middlewares.cpython-36.pyc
django_lare/__pycache__/mixins.cpython-36.pyc
django_lare/__pycache__/models.cpython-36.pyc
django_lare/__pycache__/test_settings.cpython-36.pyc
django_lare/__pycache__/test_views.cpython-36.pyc
django_lare/__pycache__/tests.cpython-36.pyc
django_lare/runtests/__init__.py
django_lare/runtests/runtests.py
django_lare/runtests/__pycache__/__init__.cpython-36.pyc
django_lare/templates/.DS_Store
django_lare/templates/django_lare/lare.html
django_lare/templates/tests/base.html
django_lare/templates/tests/no_lare_page.html
django_lare/templates/tests/page_1.html
django_lare/templates/tests/page_1_content_1.html
django_lare/templates/tests/page_1_content_1_inner_content_1.html
django_lare/templates/tests/page_1_content_1_inner_content_2.html
django_lare/templates/tests/page_1_content_2.html
django_lare/templates/tests/page_2.html
django_lare/templatetags/__init__.py
django_lare/templatetags/lare_extends.py
django_lare/templatetags/__pycache__/__init__.cpython-36.pyc
django_lare/templatetags/__pycache__/lare_extends.cpython-36.pyc