Metadata-Version: 1.1
Name: django-lare
Version: 2.0.0
Summary: Lare extension to use lare.js easily!
Home-page: http://lare-team.de
Author: Lare Team
Author-email: lare-team@lare.team
License: MIT
Platform: UNKNOWN
Classifier: Development Status :: 5 - Production/Stable
Classifier: Environment :: Web Environment
Classifier: Framework :: Django
Classifier: Intended Audience :: Developers
Classifier: Operating System :: OS Independent
Classifier: Programming Language :: Python
Classifier: Programming Language :: Python :: 3
Classifier: Topic :: Internet :: WWW/HTTP
